django_quanttide/__init__.py
django_quanttide/apps.py
django_quanttide/models/__init__.py
django_quanttide/models/choices.py
django_quanttide/models/fields.py
django_quanttide/models/models.py
django_quanttide/models/polymorphic.py
django_quanttide/serializers/__init__.py
django_quanttide/serializers/polymorphic.py
django_quanttide-0.1.0b6.dist-info/METADATA
django_quanttide-0.1.0b6.dist-info/WHEEL
django_quanttide-0.1.0b6.dist-info/RECORD
