Metadata-Version: 2.1
Name: django-quanttide
Version: 0.1.0b6
Summary: 量潮Django工具箱
License: Apache 2.0
Author: QuantTide Inc.
Author-email: opensource@quanttide.com
Requires-Python: >=3.8,<4.0
Classifier: License :: Other/Proprietary License
Classifier: Programming Language :: Python :: 3
Classifier: Programming Language :: Python :: 3.8
Classifier: Programming Language :: Python :: 3.9
Classifier: Programming Language :: Python :: 3.10
Classifier: Programming Language :: Python :: 3.11
Requires-Dist: Django (>=3.1)
Requires-Dist: django-polymorphic (>=3.1.0,<4.0.0)
Requires-Dist: django-rest-polymorphic (>=0.1.10,<0.2.0)
Requires-Dist: djangorestframework (>=3.0)
